README.md
setup.py
extradtypes/__init__.py
extradtypes/mostrecentdict.py
extradtypes.egg-info/PKG-INFO
extradtypes.egg-info/SOURCES.txt
extradtypes.egg-info/dependency_links.txt
extradtypes.egg-info/top_level.txt